{
  "version": "0.20.0",
  "released": "2026-07-10",
  "download_url": "https://github.com/dsharma01/ThetaPrime-Dist/releases/download/v0.20.0/ThetaPrime-0.20.0-setup.exe",
  "release_notes": "**Iron butterfly, single-leg, and vertical spread structures** in the Strategy Composer: `iron_butterfly` (ATM-shorted iron condor variant), single-leg blocks (short/long call, short/long put), and credit/debit vertical spreads. **Template loader** in the Strategy Composer: a dropdown to load pre-built recipes (matching `docs/composer-strategy-examples.md`) into the working draft. Selecting one only fills the browser draft \u2014 nothing is saved or schedulable until reviewed and explicitly saved.",
  "min_supported": "0.20.0"
}
